[
  {
    "id": "grammar_gp13_001",
    "grammar_point": "〜たりとも",
    "correct_answer": 2,
    "options": ["といえども", "たりとも", "んがため", "にもまして"],
    "full_response": "---\n**問題 1**\n\n＿＿＿に入る最も適切なものを選んでください。\n\n試験中は一秒＿＿＿無駄にするな。\n\n1. といえども\n2. たりとも\n3. んがため\n4. にもまして\n\n---",
    "answer_response": "正解は **2** です。\n\n「たりとも」表示「即使一~也（不能）」，常與否定句一起使用，強調連最小的單位都不被允許浪費或忽視。本句是「即使一秒也不能浪費」。\n\n**〜たりとも** 的用法：\n- 接續：数量詞（一秒・一円・一人）+ たりとも\n- 意味：即使~也~（後接否定）\n- 語感：命令語氣，強調嚴格要求\n\n繼續下一題？"
  },
  {
    "id": "grammar_gp13_002",
    "grammar_point": "〜たりとも",
    "correct_answer": 4,
    "options": ["ばこそ", "ものを", "が早いか", "たりとも"],
    "full_response": "---\n**問題 2**\n\n＿＿＿に入る最も適切なものを選んでください。\n\n工場内では一円＿＿＿コストを無駄にしてはならない。\n\n1. ばこそ\n2. ものを\n3. が早いか\n4. たりとも\n\n---",
    "answer_response": "正解は **4** です。\n\n「たりとも」後接否定，表示連最小的量也不允許浪費。本句是商業場景：「即使一日圓也不能浪費成本」。\n\n**〜たりとも〜ない** 的用法：\n- 接續：数量詞 + たりとも + 否定\n- 意味：連~也不~（強調不允許任何例外）\n- 常見搭配：一秒・一円・一人・一歩\n\n繼續下一題？"
  },
  {
    "id": "grammar_gp13_003",
    "grammar_point": "〜たりとも",
    "correct_answer": 1,
    "options": ["たりとも", "極まりない", "までもない", "如何で"],
    "full_response": "---\n**問題 3**\n\n＿＿＿に入る最も適切なものを選んでください。\n\n軍の規律において、一兵士＿＿＿命令に背くことは許されない。\n\n1. たりとも\n2. 極まりない\n3. までもない\n4. 如何で\n\n---",
    "answer_response": "正解は **1** です。\n\n「〜たりとも〜ない」表示「即使一個也不允許~」。本句為軍事場景，強調紀律：「即使是一個士兵也不被允許違抗命令」。\n\n**〜たりとも** 的用法：\n- 接續：一 + 量詞 + たりとも\n- 意味：即使一個/一次也不~\n- 語感：嚴肅、強制性，多用於規定、禁令\n\n繼續下一題？"
  },
  {
    "id": "grammar_gp13_004",
    "grammar_point": "〜たりとも",
    "correct_answer": 3,
    "options": ["といえども", "にもまして", "たりとも", "んがため"],
    "full_response": "---\n**問題 4**\n\n＿＿＿に入る最も適切なものを選んでください。\n\n患者の命がかかっている手術では、一分一秒＿＿＿おろそかにできない。\n\n1. といえども\n2. にもまして\n3. たりとも\n4. んがため\n\n---",
    "answer_response": "正解は **3** です。\n\n「一分一秒たりとも」是慣用表達，意為「即使是一分一秒也不能」。本句為醫療場景，強調每一秒的重要性。\n\n**〜たりとも** 的用法：\n- 慣用句：「一分一秒たりとも〜ない」\n- 意味：分秒必爭，絲毫不能輕視\n- 語感：語氣強烈，強調緊迫感\n\n繼續下一題？"
  },
  {
    "id": "grammar_gp13_005",
    "grammar_point": "〜たりとも",
    "correct_answer": 2,
    "options": ["ばこそ", "たりとも", "が早いか", "ものを"],
    "full_response": "---\n**問題 5**\n\n＿＿＿に入る最も適切なものを選んでください。\n\n個人情報の管理において、一件＿＿＿漏洩は絶対に避けなければならない。\n\n1. ばこそ\n2. たりとも\n3. が早いか\n4. ものを\n\n---",
    "answer_response": "正解は **2** です。\n\n「たりとも」強調即使是最小的單位也不允許，此處是「即使一件個資外洩也絕對不允許」，場景為資訊安全領域。\n\n**〜たりとも** 總整理：\n- 接續：一 + 量詞（秒・円・人・件・歩）+ たりとも\n- 後接：否定表達（〜ない・〜てはならない・〜できない）\n- 意味：連最小的單位也不能~\n- 近義：〜でさえ〜ない（較口語）\n\n繼續下一題？"
  }
]
